linking/__init__.py
linking/main.py
entity_linking-0.0.1.0.dist-info/METADATA
entity_linking-0.0.1.0.dist-info/WHEEL
entity_linking-0.0.1.0.dist-info/top_level.txt
entity_linking-0.0.1.0.dist-info/RECORD
