Metadata-Version: 2.1
Name: entity-linking
Version: 0.0.1.0
Summary: A library for lightweight entity linking
Author: Nikolas
Requires-Python: >=3.10
Requires-Dist: numpy==1.26.4
Requires-Dist: SPARQLWrapper==2.0.0
Requires-Dist: sentence-transformers==3.1.1
Requires-Dist: aiohttp==3.9.5
Requires-Dist: openai==1.54.2
Requires-Dist: beautifulsoup4==4.12.2
Requires-Dist: fake-useragent==1.5.1
